django_admin_search_fields/__init__.py
django_admin_search_fields/admin.py
django_admin_search_fields/apps.py
django_admin_search_fields/static/django_admin_search_fields/search.css
django_admin_search_fields/static/django_admin_search_fields/search.js
django_admin_search_fields/templates/django_admin_search_fields/change_list.html
django_admin_search_fields/templates/django_admin_search_fields/search_form.html
django_admin_search_fields/templatetags/__init__.py
django_admin_search_fields/templatetags/dasf_tags.py
django_admin_search_fields-0.1.3.dist-info/LICENSE
django_admin_search_fields-0.1.3.dist-info/METADATA
django_admin_search_fields-0.1.3.dist-info/WHEEL
django_admin_search_fields-0.1.3.dist-info/top_level.txt
django_admin_search_fields-0.1.3.dist-info/RECORD
