Metadata-Version: 2.1
Name: django-admin-search-fields
Version: 0.1.3
Summary: django-admin-search-fields allows users to dynamically selecting search fields on list page
Author-email: Ishak Okutan <ishak.oktn@gmail.com>
License: BSD 3-Clause License
Project-URL: Documentation, https://github.com/ishakoktn/django-admin-search-fields/blob/master/README.md
Project-URL: Homepage, https://github.com/ishakoktn/django-admin-search-fields
Project-URL: Repository, https://github.com/ishakoktn/django-admin-search-fields
Classifier: Development Status :: 5 - Production/Stable
Classifier: Environment :: Web Environment
Classifier: Framework :: Django
Classifier: Framework :: Django :: 3.2
Classifier: Framework :: Django :: 4.2
Classifier: Framework :: Django :: 5.0
Classifier: Intended Audience :: Developers
Classifier: License :: OSI Approved :: BSD License
Classifier: Operating System :: OS Independent
Classifier: Programming Language :: Python
Classifier: Programming Language :: Python :: 3
Classifier: Programming Language :: Python :: 3.8
Classifier: Programming Language :: Python :: 3.9
Classifier: Programming Language :: Python :: 3.10
Classifier: Programming Language :: Python :: 3.11
Classifier: Programming Language :: Python :: 3.12
Classifier: Topic :: Utilities
License-File: LICENSE
Requires-Dist: django >=3.2
